{"v":"5.7.1","fr":25,"ip":0,"op":80,"w":800,"h":610,"nm":"网页登录动效分层稿1280","ddd":0,"assets":[{"id":"image_0","w":707,"h":406,"u":"images/","p":"img_0.png","e":0},{"id":"image_1","w":63,"h":158,"u":"images/","p":"img_1.png","e":0},{"id":"image_2","w":215,"h":165,"u":"images/","p":"img_2.png","e":0},{"id":"image_3","w":134,"h":120,"u":"images/","p":"img_3.png","e":0},{"id":"image_4","w":263,"h":283,"u":"images/","p":"img_4.png","e":0},{"id":"image_5","w":110,"h":65,"u":"images/","p":"img_5.png","e":0},{"id":"image_6","w":220,"h":152,"u":"images/","p":"img_6.png","e":0},{"id":"image_7","w":49,"h":66,"u":"images/","p":"img_7.png","e":0},{"id":"image_8","w":150,"h":102,"u":"images/","p":"img_8.png","e":0},{"id":"image_9","w":166,"h":223,"u":"images/","p":"img_9.png","e":0},{"id":"image_10","w":48,"h":50,"u":"images/","p":"img_10.png","e":0},{"id":"image_11","w":209,"h":136,"u":"images/","p":"img_11.png","e":0},{"id":"image_12","w":515,"h":341,"u":"images/","p":"img_12.png","e":0},{"id":"image_13","w":785,"h":481,"u":"images/","p":"img_13.png","e":0}],"layers":[{"ddd":0,"ind":1,"ty":2,"nm":"小人","refId":"image_0","sr":1,"ks":{"o":{"a":0,"k":100,"ix":11},"r":{"a":0,"k":0,"ix":10},"p":{"a":0,"k":[354.069,383.138,0],"ix":2},"a":{"a":0,"k":[353.225,202.91,0],"ix":1},"s":{"a":0,"k":[100,100,100],"ix":6}},"ao":0,"ip":0,"op":80,"st":0,"bm":0},{"ddd":0,"ind":2,"ty":2,"nm":"云-电子信号","refId":"image_1","sr":1,"ks":{"o":{"a":0,"k":100,"ix":11},"r":{"a":0,"k":0,"ix":10},"p":{"a":0,"k":[681.523,420.781,0],"ix":2},"a":{"a":0,"k":[31.073,78.507,0],"ix":1},"s":{"a":0,"k":[100,100,100],"ix":6}},"ao":0,"hasMask":true,"masksProperties":[{"inv":false,"mode":"a","pt":{"a":1,"k":[{"i":{"x":0.667,"y":1},"o":{"x":0.333,"y":0},"t":0,"s":[{"i":[[0,0],[0,0],[0,0],[0,0]],"o":[[0,0],[0,0],[0,0],[0,0]],"v":[[71.05,162.726],[-0.95,162.726],[-1.2,163.226],[70.55,162.726]],"c":true}]},{"i":{"x":0.667,"y":1},"o":{"x":0.333,"y":0},"t":35,"s":[{"i":[[0,0],[0,0],[0,0],[0,0]],"o":[[0,0],[0,0],[0,0],[0,0]],"v":[[69.05,9.726],[-6.45,10.226],[-1.2,163.226],[70.55,162.726]],"c":true}]},{"i":{"x":0.667,"y":1},"o":{"x":0.333,"y":0},"t":40,"s":[{"i":[[0,0],[0,0],[0,0],[0,0]],"o":[[0,0],[0,0],[0,0],[0,0]],"v":[[69.05,9.726],[-6.45,10.226],[-1.2,163.226],[70.55,162.726]],"c":true}]},{"t":74,"s":[{"i":[[0,0],[0,0],[0,0],[0,0]],"o":[[0,0],[0,0],[0,0],[0,0]],"v":[[71.05,162.726],[-0.95,162.726],[-1.2,163.226],[70.55,162.726]],"c":true}]}],"ix":1},"o":{"a":0,"k":100,"ix":3},"x":{"a":0,"k":0,"ix":4},"nm":"蒙版 1"}],"ip":0,"op":80,"st":0,"bm":0},{"ddd":0,"ind":3,"ty":2,"nm":"云","refId":"image_2","sr":1,"ks":{"o":{"a":0,"k":100,"ix":11},"r":{"a":0,"k":0,"ix":10},"p":{"a":0,"k":[656.825,508.909,0],"ix":2},"a":{"a":0,"k":[107.43,82.185,0],"ix":1},"s":{"a":0,"k":[100,100,100],"ix":6}},"ao":0,"ip":0,"op":80,"st":0,"bm":0},{"ddd":0,"ind":4,"ty":2,"nm":"计算机-柱状图","refId":"image_3","sr":1,"ks":{"o":{"a":0,"k":100,"ix":11},"r":{"a":0,"k":0,"ix":10},"p":{"a":0,"k":[658.814,136.647,0],"ix":2},"a":{"a":0,"k":[66.994,59.538,0],"ix":1},"s":{"a":0,"k":[100,100,100],"ix":6}},"ao":0,"hasMask":true,"masksProperties":[{"inv":false,"mode":"a","pt":{"a":1,"k":[{"i":{"x":0.667,"y":1},"o":{"x":0.333,"y":0},"t":0,"s":[{"i":[[0,0],[0.25,0],[0,0],[0,0]],"o":[[0,0],[-0.25,0],[0,0],[0,0]],"v":[[-0.32,46.89],[-0.82,46.89],[135.18,124.89],[135.18,124.64]],"c":true}]},{"i":{"x":0.667,"y":1},"o":{"x":0.333,"y":0},"t":35,"s":[{"i":[[0,0],[0.25,0],[0,0],[0,0]],"o":[[0,0],[-0.25,0],[0,0],[0,0]],"v":[[-0.32,-19.36],[-0.82,46.89],[135.18,124.89],[135.68,52.64]],"c":true}]},{"i":{"x":0.667,"y":1},"o":{"x":0.333,"y":0},"t":40,"s":[{"i":[[0,0],[0.25,0],[0,0],[0,0]],"o":[[0,0],[-0.25,0],[0,0],[0,0]],"v":[[-0.32,-19.36],[-0.82,46.89],[135.18,124.89],[135.68,52.64]],"c":true}]},{"t":74,"s":[{"i":[[0,0],[0.25,0],[0,0],[0,0]],"o":[[0,0],[-0.25,0],[0,0],[0,0]],"v":[[-0.32,46.89],[-0.82,46.89],[135.18,124.89],[135.18,124.64]],"c":true}]}],"ix":1},"o":{"a":0,"k":100,"ix":3},"x":{"a":0,"k":0,"ix":4},"nm":"蒙版 1"}],"ip":0,"op":80,"st":0,"bm":0},{"ddd":0,"ind":5,"ty":2,"nm":"计算机","refId":"image_4","sr":1,"ks":{"o":{"a":0,"k":100,"ix":11},"r":{"a":0,"k":0,"ix":10},"p":{"a":0,"k":[610.088,146.706,0],"ix":2},"a":{"a":0,"k":[131.05,141.079,0],"ix":1},"s":{"a":0,"k":[100,100,100],"ix":6}},"ao":0,"ip":0,"op":80,"st":0,"bm":0},{"ddd":0,"ind":6,"ty":2,"nm":"前台-曲线","refId":"image_5","sr":1,"ks":{"o":{"a":0,"k":100,"ix":11},"r":{"a":0,"k":0,"ix":10},"p":{"a":1,"k":[{"i":{"x":0.667,"y":1},"o":{"x":0.333,"y":0},"t":0,"s":[171.401,490.109,0],"to":[0,-1.5,0],"ti":[0,1.5,0]},{"i":{"x":0.667,"y":0.667},"o":{"x":0.333,"y":0.333},"t":35,"s":[171.401,481.109,0],"to":[0,0,0],"ti":[0,0,0]},{"i":{"x":0.833,"y":1},"o":{"x":0.333,"y":0},"t":40,"s":[171.401,481.109,0],"to":[0,1.5,0],"ti":[0,-1.5,0]},{"t":74,"s":[171.401,490.109,0]}],"ix":2},"a":{"a":0,"k":[54.978,32.002,0],"ix":1},"s":{"a":0,"k":[100,100,100],"ix":6}},"ao":0,"ef":[{"ty":5,"nm":"径向阴影","np":11,"mn":"ADBE Radial Shadow","ix":1,"en":1,"ef":[{"ty":2,"nm":"阴影颜色","mn":"ADBE Radial Shadow-0001","ix":1,"v":{"a":0,"k":[0.525490224361,0.57647061348,0.800000071526,1],"ix":1}},{"ty":0,"nm":"不透明度","mn":"ADBE Radial Shadow-0002","ix":2,"v":{"a":0,"k":0.3,"ix":2}},{"ty":3,"nm":"光源","mn":"ADBE Radial Shadow-0003","ix":3,"v":{"a":0,"k":[20.75,5.75],"ix":3}},{"ty":0,"nm":"投影距离","mn":"ADBE Radial Shadow-0004","ix":4,"v":{"a":0,"k":6,"ix":4}},{"ty":0,"nm":"柔和度","mn":"ADBE Radial Shadow-0005","ix":5,"v":{"a":0,"k":0,"ix":5}},{"ty":7,"nm":"渲染","mn":"ADBE Radial Shadow-0006","ix":6,"v":{"a":0,"k":1,"ix":6}},{"ty":0,"nm":"颜色影响","mn":"ADBE Radial Shadow-0007","ix":7,"v":{"a":0,"k":1,"ix":7}},{"ty":7,"nm":"仅阴影","mn":"ADBE Radial Shadow-0008","ix":8,"v":{"a":0,"k":0,"ix":8}},{"ty":7,"nm":"调整图层大小","mn":"ADBE Radial Shadow-0009","ix":9,"v":{"a":0,"k":0,"ix":9}}]}],"ip":0,"op":80,"st":0,"bm":0},{"ddd":0,"ind":7,"ty":2,"nm":"前台","refId":"image_6","sr":1,"ks":{"o":{"a":0,"k":100,"ix":11},"r":{"a":0,"k":0,"ix":10},"p":{"a":0,"k":[148.243,516.31,0],"ix":2},"a":{"a":0,"k":[109.617,75.996,0],"ix":1},"s":{"a":0,"k":[100,100,100],"ix":6}},"ao":0,"ip":0,"op":80,"st":0,"bm":0},{"ddd":0,"ind":8,"ty":2,"nm":"打印机-文件","refId":"image_7","sr":1,"ks":{"o":{"a":0,"k":100,"ix":11},"r":{"a":0,"k":0,"ix":10},"p":{"a":1,"k":[{"i":{"x":0.667,"y":1},"o":{"x":0.333,"y":0},"t":0,"s":[178.156,160.637,0],"to":[0,-1.667,0],"ti":[0,1.667,0]},{"i":{"x":0.667,"y":0.667},"o":{"x":0.333,"y":0.333},"t":35,"s":[178.156,150.637,0],"to":[0,0,0],"ti":[0,0,0]},{"i":{"x":0.833,"y":1},"o":{"x":0.333,"y":0},"t":40,"s":[178.156,150.637,0],"to":[0,1.667,0],"ti":[0,-1.667,0]},{"t":74,"s":[178.156,160.637,0]}],"ix":2},"a":{"a":0,"k":[24.248,32.833,0],"ix":1},"s":{"a":0,"k":[100,100,100],"ix":6}},"ao":0,"ip":0,"op":80,"st":0,"bm":0},{"ddd":0,"ind":9,"ty":2,"nm":"打印机","refId":"image_8","sr":1,"ks":{"o":{"a":0,"k":100,"ix":11},"r":{"a":0,"k":0,"ix":10},"p":{"a":0,"k":[191.663,197.098,0],"ix":2},"a":{"a":0,"k":[74.624,50.824,0],"ix":1},"s":{"a":0,"k":[100,100,100],"ix":6}},"ao":0,"ip":0,"op":80,"st":0,"bm":0},{"ddd":0,"ind":10,"ty":2,"nm":"中台红-射灯","refId":"image_9","sr":1,"ks":{"o":{"a":0,"k":100,"ix":11},"r":{"a":0,"k":0,"ix":10},"p":{"a":0,"k":[382.406,255.018,0],"ix":2},"a":{"a":0,"k":[82.926,111.033,0],"ix":1},"s":{"a":0,"k":[100,100,100],"ix":6}},"ao":0,"ef":[{"ty":5,"nm":"线性擦除","np":5,"mn":"ADBE Linear Wipe","ix":1,"en":1,"ef":[{"ty":0,"nm":"过渡完成","mn":"ADBE Linear Wipe-0001","ix":1,"v":{"a":1,"k":[{"i":{"x":[0.667],"y":[1]},"o":{"x":[0.333],"y":[0]},"t":0,"s":[80]},{"i":{"x":[0.667],"y":[1]},"o":{"x":[0.333],"y":[0]},"t":35,"s":[10]},{"i":{"x":[0.833],"y":[1]},"o":{"x":[0.333],"y":[0]},"t":40,"s":[10]},{"t":74,"s":[80]}],"ix":1}},{"ty":0,"nm":"擦除角度","mn":"ADBE Linear Wipe-0002","ix":2,"v":{"a":0,"k":180,"ix":2}},{"ty":0,"nm":"羽化","mn":"ADBE Linear Wipe-0003","ix":3,"v":{"a":0,"k":136,"ix":3}}]}],"ip":0,"op":80,"st":0,"bm":0},{"ddd":0,"ind":11,"ty":2,"nm":"中台红-粒子","refId":"image_10","sr":1,"ks":{"o":{"a":1,"k":[{"i":{"x":[0.667],"y":[1]},"o":{"x":[0.333],"y":[0]},"t":0,"s":[50]},{"i":{"x":[0.667],"y":[1]},"o":{"x":[0.333],"y":[0]},"t":35,"s":[100]},{"i":{"x":[0.833],"y":[1]},"o":{"x":[0.333],"y":[0]},"t":40,"s":[100]},{"t":74,"s":[50]}],"ix":11},"r":{"a":0,"k":0,"ix":10},"p":{"a":1,"k":[{"i":{"x":0.667,"y":1},"o":{"x":0.333,"y":0},"t":0,"s":[383.85,268.87,0],"to":[0,-1.962,0],"ti":[0,1.205,0]},{"i":{"x":0.667,"y":1},"o":{"x":0.333,"y":0},"t":35,"s":[383.85,256.12,0],"to":[0,0,0],"ti":[0,1.205,0]},{"i":{"x":0.833,"y":1},"o":{"x":0.333,"y":0},"t":40,"s":[383.85,256.12,0],"to":[0,0,0],"ti":[0,3.167,0]},{"t":74,"s":[383.85,268.87,0]}],"ix":2},"a":{"a":0,"k":[23.967,24.721,0],"ix":1},"s":{"a":1,"k":[{"i":{"x":[0.667,0.667,0.667],"y":[1,1,1]},"o":{"x":[0.333,0.333,0.333],"y":[0,0,0]},"t":0,"s":[95,95,100]},{"i":{"x":[0.667,0.667,0.667],"y":[1,1,1]},"o":{"x":[0.333,0.333,0.333],"y":[0,0,0]},"t":35,"s":[100,100,100]},{"i":{"x":[0.833,0.833,0.833],"y":[1,1,1]},"o":{"x":[0.333,0.333,0.333],"y":[0,0,0]},"t":40,"s":[100,100,100]},{"t":74,"s":[95,95,100]}],"ix":6}},"ao":0,"ip":0,"op":80,"st":0,"bm":0},{"ddd":0,"ind":12,"ty":2,"nm":"中台红","refId":"image_11","sr":1,"ks":{"o":{"a":0,"k":100,"ix":11},"r":{"a":0,"k":0,"ix":10},"p":{"a":0,"k":[392.5,364.168,0],"ix":2},"a":{"a":0,"k":[104.5,67.832,0],"ix":1},"s":{"a":0,"k":[100,100,100],"ix":6}},"ao":0,"ip":0,"op":80,"st":0,"bm":0},{"ddd":0,"ind":13,"ty":2,"nm":"中台","refId":"image_12","sr":1,"ks":{"o":{"a":0,"k":100,"ix":11},"r":{"a":0,"k":0,"ix":10},"p":{"a":0,"k":[340.938,347.306,0],"ix":2},"a":{"a":0,"k":[257.062,170.306,0],"ix":1},"s":{"a":0,"k":[100,100,100],"ix":6}},"ao":0,"ip":0,"op":80,"st":0,"bm":0},{"ddd":0,"ind":14,"ty":2,"nm":"固定小零件","refId":"image_13","sr":1,"ks":{"o":{"a":0,"k":100,"ix":11},"r":{"a":0,"k":0,"ix":10},"p":{"a":0,"k":[405.212,361.035,0],"ix":2},"a":{"a":0,"k":[392.066,240.003,0],"ix":1},"s":{"a":0,"k":[100,100,100],"ix":6}},"ao":0,"ip":0,"op":80,"st":0,"bm":0}],"markers":[]}